mailpit/__init__.py
mailpit/client/__init__.py
mailpit/client/api.py
mailpit/client/models.py
mailpit/testing/__init__.py
mailpit/testing/pytest.py
mailpit/testing/unittest.py
mailpit_api_client-1.0.0.dist-info/LICENSE
mailpit_api_client-1.0.0.dist-info/METADATA
mailpit_api_client-1.0.0.dist-info/WHEEL
mailpit_api_client-1.0.0.dist-info/top_level.txt
mailpit_api_client-1.0.0.dist-info/RECORD
