Metadata-Version: 2.1
Name: mailpit-api-client
Version: 1.0.0
Summary: A Mailpit API Client
Author-email: Lars Liedtke <lars@familie-liedtke.net>
License: GNU LESSER GENERAL PUBLIC LICENSE
Project-URL: Repository, https://github.com/Corvan/mailpit-api-client
Project-URL: Documentation, https://corvan.github.io/mailpit-api-client/
Classifier: Framework :: Pytest
Classifier: Intended Audience :: Developers
Classifier: License :: OSI Approved :: GNU Lesser General Public License v3 (LGPLv3)
Classifier: Programming Language :: Python :: 3.8
Classifier: Programming Language :: Python :: 3.9
Classifier: Programming Language :: Python :: 3.10
Classifier: Programming Language :: Python :: 3.11
Classifier: Programming Language :: Python :: 3.12
Classifier: Topic :: Communications :: Email
Classifier: Topic :: Communications :: Email :: Mail Transport Agents
Classifier: Topic :: Software Development :: Libraries :: Python Modules
Classifier: Topic :: Software Development :: Testing
Classifier: Topic :: Utilities
Requires-Python: >=3.8
License-File: LICENSE
Requires-Dist: dataclasses-json
Requires-Dist: httpx
Requires-Dist: ruff
Requires-Dist: invoke (>=2.0.0)
Requires-Dist: logging518 (>=1.0.0)
Provides-Extra: build
Requires-Dist: build ; extra == 'build'
Requires-Dist: twine ; extra == 'build'
Provides-Extra: docs
Requires-Dist: Sphinx ; extra == 'docs'
Provides-Extra: pytest
Requires-Dist: mailpit-api-client[test] ; extra == 'pytest'
Requires-Dist: pytest (>=7) ; extra == 'pytest'
Provides-Extra: test
Requires-Dist: black ; extra == 'test'
Requires-Dist: mypy (>=1.1.1) ; extra == 'test'
Requires-Dist: pylint ; extra == 'test'
Requires-Dist: respx ; extra == 'test'
